linechart_animator/__init__.py
linechart_animator/animator.py
linechart_animator-0.0.10.dist-info/METADATA
linechart_animator-0.0.10.dist-info/WHEEL
linechart_animator-0.0.10.dist-info/top_level.txt
linechart_animator-0.0.10.dist-info/RECORD
