Metadata-Version: 2.1
Name: linechart-animator
Version: 0.0.10
Summary: Create animated plots
Home-page: https://github.com/Zselter07/linechart_animator
Author: Péntek Zsolt
License: UNKNOWN
Platform: UNKNOWN
Classifier: Programming Language :: Python :: 3
Classifier: License :: OSI Approved :: MIT License
Classifier: Operating System :: OS Independent
Requires-Python: >=3.6
Requires-Dist: numpy
Requires-Dist: matplotlib
Requires-Dist: scipy
